cool_trading/__init__.py
cool_trading/config.py
cool_trading/api/__init__.py
cool_trading/api/constant.py
cool_trading/api/event.py
cool_trading/api/function.py
cool_trading/api/gateway.py
cool_trading/api/huobi.py
cool_trading/api/object.py
cool_trading/api/rest_client.py
cool_trading/api/websocket_client.py
cool_trading/run/__init__.py
cool_trading/run/runrestspider/__init__.py
cool_trading/run/runwebsocketspider/__init__.py
cool_trading/serivice/__init__.py
cool_trading/serivice/mqservice.py
cool_trading/serivice/redisservice.py
cool_trading/spider/__init__.py
cool_trading/spider/test.py
cool_trading/spider/restspider/__init__.py
cool_trading/spider/websocketspider/__init__.py
cool_trading/strategy/__init__.py
cool_trading/strategy/strategyTemplate.py
cool_trading-1.0.1.dist-info/LICENSE
cool_trading-1.0.1.dist-info/METADATA
cool_trading-1.0.1.dist-info/WHEEL
cool_trading-1.0.1.dist-info/top_level.txt
cool_trading-1.0.1.dist-info/RECORD
