Metadata-Version: 2.1
Name: cool-trading
Version: 1.0.1
Summary: One trading system 
Home-page: https://www.8btc.com/
Author: ipqhjjybj
Author-email: 250657661@qq.com
License: AGPL v3
Platform: UNKNOWN
Classifier: Development Status :: 3 - Alpha
Classifier: Intended Audience :: Developers
Classifier: Topic :: Software Development :: Build Tools
Classifier: License :: OSI Approved :: MIT License
Classifier: Programming Language :: Python :: 2
Classifier: Programming Language :: Python :: 2.7
Classifier: Programming Language :: Python :: 3
Classifier: Programming Language :: Python :: 3.3
Classifier: Programming Language :: Python :: 3.4
Classifier: Programming Language :: Python :: 3.5
Requires-Dist: redis (>=2.10.5)
Requires-Dist: pika (>=1.1.0)
